replay/__init__.py
replay/price.py
replay/refit.py
replay/roller_rebalance.py
trading_replay-0.1.3.dist-info/METADATA
trading_replay-0.1.3.dist-info/WHEEL
trading_replay-0.1.3.dist-info/top_level.txt
trading_replay-0.1.3.dist-info/RECORD
