Metadata-Version: 2.1
Name: trading-replay
Version: 0.1.3
Summary: A set of redis libraries
Home-page: UNKNOWN
License: UNKNOWN
Platform: UNKNOWN
Classifier: Programming Language :: Python :: 3
Classifier: License :: OSI Approved :: MIT License
Classifier: Operating System :: OS Independent
Requires-Dist: redis
Requires-Dist: rolling
